ab_client/user/__init__.py
ab_client/user/clients/__init__.py
ab_client/user/clients/async_client.py
ab_client/user/clients/sync_client.py
ab_client/user/exceptions/__init__.py
ab_client/user/exceptions/http_exception.py
ab_client/user/models/HTTPValidationError.py
ab_client/user/models/UpsertByOIDCRequest.py
ab_client/user/models/User.py
ab_client/user/models/ValidationError.py
ab_client/user/models/__init__.py
ab_client_user-1.1.1.dist-info/METADATA
ab_client_user-1.1.1.dist-info/WHEEL
ab_client_user-1.1.1.dist-info/licenses/LICENSE
ab_client_user-1.1.1.dist-info/RECORD
